{
  "entry": {
    "precision": 1.0,
    "recall": 1.0,
    "f1-score": 1.0,
    "support": 7,
    "confused_with": {}
  },
  "name": {
    "precision": 1.0,
    "recall": 1.0,
    "f1-score": 1.0,
    "support": 5,
    "confused_with": {}
  },
  "compare_2": {
    "precision": 1.0,
    "recall": 1.0,
    "f1-score": 1.0,
    "support": 1,
    "confused_with": {}
  },
  "micro avg": {
    "precision": 1.0,
    "recall": 1.0,
    "f1-score": 1.0,
    "support": 13
  },
  "macro avg": {
    "precision": 1.0,
    "recall": 1.0,
    "f1-score": 1.0,
    "support": 13
  },
  "weighted avg": {
    "precision": 1.0,
    "recall": 1.0,
    "f1-score": 1.0,
    "support": 13
  }
}